llamaforge/__init__.py
llamaforge/config.py
llamaforge/forge.py
llamaforge/main.py
llamaforge/model.py
llamaforge/py.typed
llamaforge/server.py
llamaforge/backends/__init__.py
llamaforge/backends/base.py
llamaforge/backends/huggingface.py
llamaforge/backends/llama_cpp.py
llamaforge/backends/openai_api.py
llamaforge/plugins/__init__.py
llamaforge/plugins/base.py
llamaforge/plugins/commands/__init__.py
llamaforge/plugins/commands/benchmark.py
llamaforge/plugins/postprocessing/__init__.py
llamaforge/plugins/postprocessing/text_cleaner.py
llamaforge/plugins/preprocessing/__init__.py
llamaforge/plugins/preprocessing/text_formatter.py
llamaforge/plugins/tools/__init__.py
llamaforge/plugins/tools/calculator.py
llamaforge_llamasearch-0.2.0.dist-info/METADATA
llamaforge_llamasearch-0.2.0.dist-info/WHEEL
llamaforge_llamasearch-0.2.0.dist-info/entry_points.txt
llamaforge_llamasearch-0.2.0.dist-info/licenses/LICENSE
llamaforge_llamasearch-0.2.0.dist-info/RECORD
