Metadata-Version: 2.4
Name: llamaforge-llamasearch
Version: 0.2.0
Summary: Ultimate Language Model Command Interface
Project-URL: Homepage, https://github.com/llamasearch/llamaforge
Project-URL: Bug Tracker, https://github.com/llamasearch/llamaforge/issues
Project-URL: Documentation, https://github.com/llamasearch/llamaforge/docs
Author-email: llamaforge-llamasearch <nikjois@llamasearch.ai>
License: MIT
License-File: LICENSE
Classifier: Development Status :: 4 - Beta
Classifier: Intended Audience :: Developers
Classifier: Intended Audience :: Science/Research
Classifier: License :: OSI Approved :: MIT License
Classifier: Programming Language :: Python :: 3
Classifier: Programming Language :: Python :: 3.8
Classifier: Programming Language :: Python :: 3.9
Classifier: Programming Language :: Python :: 3.10
Classifier: Programming Language :: Python :: 3.11
Classifier: Topic :: Scientific/Engineering :: Artificial Intelligence
Requires-Python: >=3.8
Requires-Dist: numpy>=1.22.0
Requires-Dist: requests>=2.28.0
Requires-Dist: rich>=12.0.0
Requires-Dist: tqdm>=4.64.0
Provides-Extra: dev
Requires-Dist: black>=23.0.0; extra == 'dev'
Requires-Dist: flake8>=6.0.0; extra == 'dev'
Requires-Dist: isort>=5.10.0; extra == 'dev'
Requires-Dist: mypy>=1.0.0; extra == 'dev'
Requires-Dist: pytest>=7.0.0; extra == 'dev'
Provides-Extra: huggingface
Requires-Dist: torch>=1.13.0; extra == 'huggingface'
Requires-Dist: transformers>=4.25.0; extra == 'huggingface'
Provides-Extra: llama-cpp
Requires-Dist: llama-cpp-python>=0.1.0; extra == 'llama-cpp'
Provides-Extra: server
Requires-Dist: fastapi>=0.95.0; extra == 'server'
Requires-Dist: uvicorn>=0.20.0; extra == 'server'
